forestci/__init__.py
forestci/calibration.py
forestci/due.py
forestci/forestci.py
forestci/version.py
forestci/tests/__init__.py
forestci/tests/test_forestci.py
forestci-0.6.dist-info/LICENSE
forestci-0.6.dist-info/METADATA
forestci-0.6.dist-info/WHEEL
forestci-0.6.dist-info/top_level.txt
forestci-0.6.dist-info/RECORD
